LICENSE
README.rst
pyproject.toml
setup.cfg
setup.py
squish/__init__.py
squish/common.py
squish/core.c
squish/diagram.py
squish/energy.c
squish/ordered.py
squish/simulation.py
squish/squish.py
squish/voronoi.c
squish.egg-info/PKG-INFO
squish.egg-info/SOURCES.txt
squish.egg-info/dependency_links.txt
squish.egg-info/entry_points.txt
squish.egg-info/not-zip-safe
squish.egg-info/requires.txt
squish.egg-info/top_level.txt