Metadata-Version: 2.1
Name: squish
Version: 0.1.6
Summary: squish is Python program which perform simulations for the flow of 'soft' or 'compressible' objects under some energy in a periodic domain.
Home-page: https://github.com/ksjdragon/squish
Author: Kenneth Jao
Author-email: ksjdragon@gmail.com
License: UNKNOWN
Project-URL: Bug Tracker, https://github.com/ksjdragon/squish/issues
Platform: UNKNOWN
Classifier: Programming Language :: Python :: 3.8
Classifier: Programming Language :: Python :: 3.9
Classifier: Programming Language :: Python :: 3.10
Classifier: License :: OSI Approved :: GNU Affero General Public License v3 or later (AGPLv3+)
Classifier: Operating System :: OS Independent
Requires-Python: >=3.8
License-File: LICENSE
